dolo/__init__.py
dolo/algos/__init__.py
dolo/algos/bruteforce_lib.py
dolo/algos/commands.py
dolo/algos/egm.py
dolo/algos/ergodic.py
dolo/algos/fb.py
dolo/algos/improved_time_iteration.py
dolo/algos/invert.py
dolo/algos/perfect_foresight.py
dolo/algos/perturbation.py
dolo/algos/perturbations_higher_order.py
dolo/algos/results.py
dolo/algos/simulations.py
dolo/algos/steady_state.py
dolo/algos/time_iteration.py
dolo/algos/value_iteration.py
dolo/compiler/__init__.py
dolo/compiler/derivatives.py
dolo/compiler/eval_formula.py
dolo/compiler/factories.py
dolo/compiler/misc.py
dolo/compiler/model.py
dolo/compiler/model_import.py
dolo/compiler/objects.py
dolo/compiler/recipes.py
dolo/compiler/recipes.yaml
dolo/config.py
dolo/linter.py
dolo/misc/__init__.py
dolo/misc/caching.py
dolo/misc/decorators.py
dolo/misc/display.py
dolo/misc/dprint.py
dolo/misc/graphs.py
dolo/misc/groot.py
dolo/misc/itprinter.py
dolo/misc/multimethod.py
dolo/misc/termcolor.py
dolo/misc/timing.py
dolo/numeric/__init__.py
dolo/numeric/decision_rule.py
dolo/numeric/discretization/__init__.py
dolo/numeric/discretization/discretization.py
dolo/numeric/discretization/quadrature.py
dolo/numeric/distribution.py
dolo/numeric/extern/__init__.py
dolo/numeric/extern/lmmcp.py
dolo/numeric/extern/qz.py
dolo/numeric/filters.py
dolo/numeric/grids.py
dolo/numeric/matrix_equations.py
dolo/numeric/misc.py
dolo/numeric/optimize/__init__.py
dolo/numeric/optimize/ncpsolve.py
dolo/numeric/optimize/newton.py
dolo/numeric/processes.py
dolo/numeric/serial_operations.py
dolo/numeric/taylor_expansion.py
dolo/numeric/tensor.py
dolo/tests/__init__.py
dolo/tests/test_caching.py
dolo/tests/test_complementarity_problems.py
dolo/tests/test_customdr.py
dolo/tests/test_egm.py
dolo/tests/test_ergodic.py
dolo/tests/test_formula_evaluation.py
dolo/tests/test_grid.py
dolo/tests/test_grids.py
dolo/tests/test_iid_processes.py
dolo/tests/test_import.py
dolo/tests/test_irf.py
dolo/tests/test_linter.py
dolo/tests/test_model_import.py
dolo-0.4.9.20.dist-info/LICENSE
dolo-0.4.9.20.dist-info/METADATA
dolo-0.4.9.20.dist-info/WHEEL
dolo-0.4.9.20.dist-info/RECORD
