Metadata-Version: 2.1
Name: dolo
Version: 0.4.9.20
Summary: Economic Modeling in Python
License: BSD-2-Clause
Author: Winant Pablo
Author-email: pablo.winant@gmail.com
Requires-Python: >=3.9,<3.12
Classifier: License :: OSI Approved :: BSD License
Classifier: Programming Language :: Python :: 3
Classifier: Programming Language :: Python :: 3.9
Classifier: Programming Language :: Python :: 3.10
Classifier: Programming Language :: Python :: 3.11
Requires-Dist: PyYAML (>=6.0,<7.0)
Requires-Dist: dolang (>=0.0.20,<0.0.21)
Requires-Dist: interpolation (>=2.2.7,<3.0.0)
Requires-Dist: matplotlib (>=3.6.0,<4.0.0)
Requires-Dist: multipledispatch (>=0.6.0,<0.7.0)
Requires-Dist: numpy (>=1.23.1)
Requires-Dist: pandas (>=1.5.0,<2.0.0)
Requires-Dist: quantecon (>=0.7.2,<0.8.0)
Requires-Dist: scipy (>=1.10,<2.0)
Requires-Dist: xarray (>=2022.6.0,<2023.0.0)
